{
  "algorithm": "HDBSCAN",
  "parameters": {
    "min_cluster_size": 30,
    "min_samples": 10
  },
  "total_clusters": 69,
  "total_noise_points": 2804,
  "hotspots": [
    {
      "cluster_id": 15,
      "center_latitude": 12.902241,
      "center_longitude": 77.598876,
      "event_count": 192,
      "dominant_event_cause": "vehicle_breakdown",
      "dominant_cause_pct": 45.8,
      "dominant_priority": "High",
      "dominant_priority_pct": 91.7,
      "associated_police_station": "Mico Layout",
      "associated_zone": "South Zone 2",
      "associated_corridor": "Bannerghata Road",
      "rank": 1
    },
    {
      "cluster_id": 21,
      "center_latitude": 13.042138,
      "center_longitude": 77.550699,
      "event_count": 183,
      "dominant_event_cause": "vehicle_breakdown",
      "dominant_cause_pct": 78.7,
      "dominant_priority": "High",
      "dominant_priority_pct": 94.0,
      "associated_police_station": "Jalahalli",
      "associated_zone": "North Zone 2",
      "associated_corridor": "ORR North 2",
      "rank": 2
    },
    {
      "cluster_id": 34,
      "center_latitude": 13.016195,
      "center_longitude": 77.560339,
      "event_count": 180,
      "dominant_event_cause": "vehicle_breakdown",
      "dominant_cause_pct": 76.1,
      "dominant_priority": "High",
      "dominant_priority_pct": 76.7,
      "associated_police_station": "Yeshwanthpura",
      "associated_zone": "West Zone 2",
      "associated_corridor": "Tumkur Road",
      "rank": 3
    },
    {
      "cluster_id": 55,
      "center_latitude": 12.965798,
      "center_longitude": 77.585785,
      "event_count": 172,
      "dominant_event_cause": "vehicle_breakdown",
      "dominant_cause_pct": 83.7,
      "dominant_priority": "High",
      "dominant_priority_pct": 98.3,
      "associated_police_station": "Halasuru Gate",
      "associated_zone": "Central Zone 2",
      "associated_corridor": "Mysore Road",
      "rank": 4
    },
    {
      "cluster_id": 22,
      "center_latitude": 13.063296,
      "center_longitude": 77.458656,
      "event_count": 150,
      "dominant_event_cause": "vehicle_breakdown",
      "dominant_cause_pct": 73.3,
      "dominant_priority": "Low",
      "dominant_priority_pct": 100.0,
      "associated_police_station": "No Police Station",
      "associated_zone": "Zone_Unknown",
      "associated_corridor": "Non-corridor",
      "rank": 5
    },
    {
      "cluster_id": 44,
      "center_latitude": 13.099383,
      "center_longitude": 77.598799,
      "event_count": 150,
      "dominant_event_cause": "vehicle_breakdown",
      "dominant_cause_pct": 69.3,
      "dominant_priority": "High",
      "dominant_priority_pct": 96.7,
      "associated_police_station": "Yelahanka",
      "associated_zone": "North Zone 2",
      "associated_corridor": "Bellary Road 2",
      "rank": 6
    },
    {
      "cluster_id": 53,
      "center_latitude": 12.997351,
      "center_longitude": 77.584415,
      "event_count": 147,
      "dominant_event_cause": "vehicle_breakdown",
      "dominant_cause_pct": 75.5,
      "dominant_priority": "High",
      "dominant_priority_pct": 100.0,
      "associated_police_station": "Sadashivanagar",
      "associated_zone": "Central Zone 2",
      "associated_corridor": "Bellary Road 1",
      "rank": 7
    },
    {
      "cluster_id": 11,
      "center_latitude": 12.969382,
      "center_longitude": 77.700629,
      "event_count": 141,
      "dominant_event_cause": "construction",
      "dominant_cause_pct": 72.3,
      "dominant_priority": "High",
      "dominant_priority_pct": 100.0,
      "associated_police_station": "HAL Old Airport",
      "associated_zone": "East Zone 1",
      "associated_corridor": "ORR East 2",
      "rank": 8
    },
    {
      "cluster_id": 65,
      "center_latitude": 12.953556,
      "center_longitude": 77.542311,
      "event_count": 139,
      "dominant_event_cause": "vehicle_breakdown",
      "dominant_cause_pct": 86.3,
      "dominant_priority": "High",
      "dominant_priority_pct": 99.3,
      "associated_police_station": "Byatarayanapura",
      "associated_zone": "West Zone 2",
      "associated_corridor": "Mysore Road",
      "rank": 9
    },
    {
      "cluster_id": 30,
      "center_latitude": 13.047518,
      "center_longitude": 77.500799,
      "event_count": 137,
      "dominant_event_cause": "vehicle_breakdown",
      "dominant_cause_pct": 79.6,
      "dominant_priority": "Low",
      "dominant_priority_pct": 59.9,
      "associated_police_station": "Chikkabanavara",
      "associated_zone": "North Zone 2",
      "associated_corridor": "Tumkur Road",
      "rank": 10
    },
    {
      "cluster_id": 1,
      "center_latitude": 12.984377,
      "center_longitude": 77.7431,
      "event_count": 132,
      "dominant_event_cause": "vehicle_breakdown",
      "dominant_cause_pct": 58.3,
      "dominant_priority": "Low",
      "dominant_priority_pct": 92.4,
      "associated_police_station": "Mahadevapura",
      "associated_zone": "East Zone 1",
      "associated_corridor": "Varthur Road",
      "rank": 11
    },
    {
      "cluster_id": 18,
      "center_latitude": 12.91926,
      "center_longitude": 77.586769,
      "event_count": 116,
      "dominant_event_cause": "accident",
      "dominant_cause_pct": 45.7,
      "dominant_priority": "Low",
      "dominant_priority_pct": 100.0,
      "associated_police_station": "Jayanagara",
      "associated_zone": "South Zone 1",
      "associated_corridor": "Non-corridor",
      "rank": 12
    },
    {
      "cluster_id": 36,
      "center_latitude": 13.040451,
      "center_longitude": 77.517649,
      "event_count": 113,
      "dominant_event_cause": "vehicle_breakdown",
      "dominant_cause_pct": 77.9,
      "dominant_priority": "High",
      "dominant_priority_pct": 100.0,
      "associated_police_station": "Peenya",
      "associated_zone": "West Zone 1",
      "associated_corridor": "Tumkur Road",
      "rank": 13
    },
    {
      "cluster_id": 50,
      "center_latitude": 12.970787,
      "center_longitude": 77.608232,
      "event_count": 109,
      "dominant_event_cause": "vehicle_breakdown",
      "dominant_cause_pct": 65.1,
      "dominant_priority": "High",
      "dominant_priority_pct": 92.7,
      "associated_police_station": "Ashok Nagar",
      "associated_zone": "Central Zone 1",
      "associated_corridor": "Mysore Road",
      "rank": 14
    },
    {
      "cluster_id": 64,
      "center_latitude": 12.958842,
      "center_longitude": 77.5549,
      "event_count": 109,
      "dominant_event_cause": "vehicle_breakdown",
      "dominant_cause_pct": 79.8,
      "dominant_priority": "High",
      "dominant_priority_pct": 99.1,
      "associated_police_station": "Chamarajpet",
      "associated_zone": "Central Zone 2",
      "associated_corridor": "Mysore Road",
      "rank": 15
    },
    {
      "cluster_id": 9,
      "center_latitude": 12.989167,
      "center_longitude": 77.506298,
      "event_count": 105,
      "dominant_event_cause": "vehicle_breakdown",
      "dominant_cause_pct": 67.6,
      "dominant_priority": "High",
      "dominant_priority_pct": 100.0,
      "associated_police_station": "Kamakshipalya",
      "associated_zone": "West Zone 1",
      "associated_corridor": "Magadi Road",
      "rank": 16
    },
    {
      "cluster_id": 45,
      "center_latitude": 13.076158,
      "center_longitude": 77.593279,
      "event_count": 105,
      "dominant_event_cause": "vehicle_breakdown",
      "dominant_cause_pct": 72.4,
      "dominant_priority": "High",
      "dominant_priority_pct": 100.0,
      "associated_police_station": "Yelahanka",
      "associated_zone": "North Zone 1",
      "associated_corridor": "Bellary Road 2",
      "rank": 17
    },
    {
      "cluster_id": 51,
      "center_latitude": 12.939615,
      "center_longitude": 77.521385,
      "event_count": 102,
      "dominant_event_cause": "vehicle_breakdown",
      "dominant_cause_pct": 80.4,
      "dominant_priority": "High",
      "dominant_priority_pct": 100.0,
      "associated_police_station": "Byatarayanapura",
      "associated_zone": "West Zone 1",
      "associated_corridor": "Mysore Road",
      "rank": 18
    },
    {
      "cluster_id": 2,
      "center_latitude": 13.050889,
      "center_longitude": 77.642456,
      "event_count": 97,
      "dominant_event_cause": "construction",
      "dominant_cause_pct": 47.4,
      "dominant_priority": "Low",
      "dominant_priority_pct": 55.7,
      "associated_police_station": "Hennuru",
      "associated_zone": "East Zone 2",
      "associated_corridor": "Airport New South Road",
      "rank": 19
    },
    {
      "cluster_id": 13,
      "center_latitude": 12.934095,
      "center_longitude": 77.689131,
      "event_count": 97,
      "dominant_event_cause": "vehicle_breakdown",
      "dominant_cause_pct": 62.9,
      "dominant_priority": "High",
      "dominant_priority_pct": 100.0,
      "associated_police_station": "HAL Old Airport",
      "associated_zone": "East Zone 1",
      "associated_corridor": "ORR East 1",
      "rank": 20
    },
    {
      "cluster_id": 38,
      "center_latitude": 13.030201,
      "center_longitude": 77.537508,
      "event_count": 95,
      "dominant_event_cause": "vehicle_breakdown",
      "dominant_cause_pct": 93.7,
      "dominant_priority": "High",
      "dominant_priority_pct": 100.0,
      "associated_police_station": "Yeshwanthpura",
      "associated_zone": "West Zone 1",
      "associated_corridor": "Tumkur Road",
      "rank": 21
    },
    {
      "cluster_id": 58,
      "center_latitude": 12.980964,
      "center_longitude": 77.570086,
      "event_count": 94,
      "dominant_event_cause": "vehicle_breakdown",
      "dominant_cause_pct": 70.2,
      "dominant_priority": "Low",
      "dominant_priority_pct": 100.0,
      "associated_police_station": "Sheshadripuram",
      "associated_zone": "Central Zone 2",
      "associated_corridor": "Non-corridor",
      "rank": 22
    },
    {
      "cluster_id": 62,
      "center_latitude": 12.977698,
      "center_longitude": 77.586462,
      "event_count": 94,
      "dominant_event_cause": "vehicle_breakdown",
      "dominant_cause_pct": 61.7,
      "dominant_priority": "Low",
      "dominant_priority_pct": 100.0,
      "associated_police_station": "Halasuru Gate",
      "associated_zone": "Central Zone 2",
      "associated_corridor": "Non-corridor",
      "rank": 23
    },
    {
      "cluster_id": 63,
      "center_latitude": 13.035981,
      "center_longitude": 77.589011,
      "event_count": 88,
      "dominant_event_cause": "vehicle_breakdown",
      "dominant_cause_pct": 67.0,
      "dominant_priority": "High",
      "dominant_priority_pct": 100.0,
      "associated_police_station": "Hebbala",
      "associated_zone": "North Zone 2",
      "associated_corridor": "Bellary Road 1",
      "rank": 24
    },
    {
      "cluster_id": 40,
      "center_latitude": 12.922627,
      "center_longitude": 77.619452,
      "event_count": 87,
      "dominant_event_cause": "vehicle_breakdown",
      "dominant_cause_pct": 44.8,
      "dominant_priority": "High",
      "dominant_priority_pct": 100.0,
      "associated_police_station": "Madiwala",
      "associated_zone": "South Zone 2",
      "associated_corridor": "Hosur Road",
      "rank": 25
    },
    {
      "cluster_id": 39,
      "center_latitude": 12.911555,
      "center_longitude": 77.626183,
      "event_count": 84,
      "dominant_event_cause": "vehicle_breakdown",
      "dominant_cause_pct": 67.9,
      "dominant_priority": "High",
      "dominant_priority_pct": 100.0,
      "associated_police_station": "HSR Layout",
      "associated_zone": "South Zone 2",
      "associated_corridor": "Hosur Road",
      "rank": 26
    },
    {
      "cluster_id": 56,
      "center_latitude": 12.983158,
      "center_longitude": 77.595791,
      "event_count": 82,
      "dominant_event_cause": "vehicle_breakdown",
      "dominant_cause_pct": 50.0,
      "dominant_priority": "High",
      "dominant_priority_pct": 100.0,
      "associated_police_station": "Cubbon Park",
      "associated_zone": "Central Zone 2",
      "associated_corridor": "CBD 2",
      "rank": 27
    },
    {
      "cluster_id": 31,
      "center_latitude": 13.009901,
      "center_longitude": 77.696421,
      "event_count": 76,
      "dominant_event_cause": "vehicle_breakdown",
      "dominant_cause_pct": 69.7,
      "dominant_priority": "Low",
      "dominant_priority_pct": 100.0,
      "associated_police_station": "K.R. Pura",
      "associated_zone": "East Zone 2",
      "associated_corridor": "Non-corridor",
      "rank": 28
    },
    {
      "cluster_id": 19,
      "center_latitude": 12.915082,
      "center_longitude": 77.568802,
      "event_count": 74,
      "dominant_event_cause": "vehicle_breakdown",
      "dominant_cause_pct": 66.2,
      "dominant_priority": "High",
      "dominant_priority_pct": 58.1,
      "associated_police_station": "Banashankari",
      "associated_zone": "South Zone 1",
      "associated_corridor": "ORR West 1",
      "rank": 29
    },
    {
      "cluster_id": 0,
      "center_latitude": 12.94073,
      "center_longitude": 77.747072,
      "event_count": 72,
      "dominant_event_cause": "vehicle_breakdown",
      "dominant_cause_pct": 33.3,
      "dominant_priority": "Low",
      "dominant_priority_pct": 100.0,
      "associated_police_station": "Whitefield",
      "associated_zone": "East Zone 1",
      "associated_corridor": "Non-corridor",
      "rank": 30
    },
    {
      "cluster_id": 23,
      "center_latitude": 12.997938,
      "center_longitude": 77.61322,
      "event_count": 72,
      "dominant_event_cause": "vehicle_breakdown",
      "dominant_cause_pct": 40.3,
      "dominant_priority": "Low",
      "dominant_priority_pct": 86.1,
      "associated_police_station": "Pulikeshinagar(F.Town)",
      "associated_zone": "North Zone 1",
      "associated_corridor": "Airport New South Road",
      "rank": 31
    },
    {
      "cluster_id": 7,
      "center_latitude": 12.966388,
      "center_longitude": 77.51443,
      "event_count": 70,
      "dominant_event_cause": "vehicle_breakdown",
      "dominant_cause_pct": 65.7,
      "dominant_priority": "Low",
      "dominant_priority_pct": 98.6,
      "associated_police_station": "Jnanabharathi",
      "associated_zone": "West Zone 1",
      "associated_corridor": "Tumkur Road",
      "rank": 32
    },
    {
      "cluster_id": 24,
      "center_latitude": 13.019492,
      "center_longitude": 77.709947,
      "event_count": 65,
      "dominant_event_cause": "vehicle_breakdown",
      "dominant_cause_pct": 84.6,
      "dominant_priority": "Low",
      "dominant_priority_pct": 100.0,
      "associated_police_station": "K.R. Pura",
      "associated_zone": "East Zone 2",
      "associated_corridor": "Non-corridor",
      "rank": 33
    },
    {
      "cluster_id": 27,
      "center_latitude": 12.990902,
      "center_longitude": 77.659214,
      "event_count": 65,
      "dominant_event_cause": "vehicle_breakdown",
      "dominant_cause_pct": 66.2,
      "dominant_priority": "High",
      "dominant_priority_pct": 63.1,
      "associated_police_station": "Banaswadi",
      "associated_zone": "Central Zone 1",
      "associated_corridor": "Old Madras Road",
      "rank": 34
    },
    {
      "cluster_id": 59,
      "center_latitude": 12.986442,
      "center_longitude": 77.573784,
      "event_count": 65,
      "dominant_event_cause": "vehicle_breakdown",
      "dominant_cause_pct": 66.2,
      "dominant_priority": "Low",
      "dominant_priority_pct": 100.0,
      "associated_police_station": "Sheshadripuram",
      "associated_zone": "Central Zone 2",
      "associated_corridor": "Non-corridor",
      "rank": 35
    },
    {
      "cluster_id": 52,
      "center_latitude": 12.978115,
      "center_longitude": 77.601183,
      "event_count": 64,
      "dominant_event_cause": "vehicle_breakdown",
      "dominant_cause_pct": 45.3,
      "dominant_priority": "High",
      "dominant_priority_pct": 96.9,
      "associated_police_station": "Cubbon Park",
      "associated_zone": "Central Zone 1",
      "associated_corridor": "Old Madras Road",
      "rank": 36
    },
    {
      "cluster_id": 8,
      "center_latitude": 12.985644,
      "center_longitude": 77.524362,
      "event_count": 63,
      "dominant_event_cause": "vehicle_breakdown",
      "dominant_cause_pct": 74.6,
      "dominant_priority": "High",
      "dominant_priority_pct": 100.0,
      "associated_police_station": "Kamakshipalya",
      "associated_zone": "West Zone 1",
      "associated_corridor": "Magadi Road",
      "rank": 37
    },
    {
      "cluster_id": 32,
      "center_latitude": 12.997898,
      "center_longitude": 77.666074,
      "event_count": 60,
      "dominant_event_cause": "vehicle_breakdown",
      "dominant_cause_pct": 63.3,
      "dominant_priority": "High",
      "dominant_priority_pct": 98.3,
      "associated_police_station": "Banaswadi",
      "associated_zone": "East Zone 2",
      "associated_corridor": "ORR North 1",
      "rank": 38
    },
    {
      "cluster_id": 42,
      "center_latitude": 12.962542,
      "center_longitude": 77.63372,
      "event_count": 60,
      "dominant_event_cause": "vehicle_breakdown",
      "dominant_cause_pct": 56.7,
      "dominant_priority": "Low",
      "dominant_priority_pct": 63.3,
      "associated_police_station": "Halasur",
      "associated_zone": "Central Zone 1",
      "associated_corridor": "Old Airport Road",
      "rank": 39
    },
    {
      "cluster_id": 68,
      "center_latitude": 13.015012,
      "center_longitude": 77.583866,
      "event_count": 59,
      "dominant_event_cause": "vehicle_breakdown",
      "dominant_cause_pct": 79.7,
      "dominant_priority": "High",
      "dominant_priority_pct": 100.0,
      "associated_police_station": "Sadashivanagar",
      "associated_zone": "West Zone 2",
      "associated_corridor": "Bellary Road 1",
      "rank": 40
    },
    {
      "cluster_id": 20,
      "center_latitude": 13.044726,
      "center_longitude": 77.582436,
      "event_count": 56,
      "dominant_event_cause": "congestion",
      "dominant_cause_pct": 67.9,
      "dominant_priority": "High",
      "dominant_priority_pct": 100.0,
      "associated_police_station": "Kodigehalli",
      "associated_zone": "North Zone 2",
      "associated_corridor": "ORR North 2",
      "rank": 41
    },
    {
      "cluster_id": 17,
      "center_latitude": 12.879948,
      "center_longitude": 77.646107,
      "event_count": 55,
      "dominant_event_cause": "vehicle_breakdown",
      "dominant_cause_pct": 67.3,
      "dominant_priority": "High",
      "dominant_priority_pct": 100.0,
      "associated_police_station": "Electronic City",
      "associated_zone": "South Zone 2",
      "associated_corridor": "Hosur Road",
      "rank": 42
    },
    {
      "cluster_id": 43,
      "center_latitude": 13.119234,
      "center_longitude": 77.609353,
      "event_count": 52,
      "dominant_event_cause": "vehicle_breakdown",
      "dominant_cause_pct": 84.6,
      "dominant_priority": "High",
      "dominant_priority_pct": 100.0,
      "associated_police_station": "Yelahanka",
      "associated_zone": "North Zone 2",
      "associated_corridor": "Bellary Road 2",
      "rank": 43
    },
    {
      "cluster_id": 49,
      "center_latitude": 12.944464,
      "center_longitude": 77.596636,
      "event_count": 51,
      "dominant_event_cause": "vehicle_breakdown",
      "dominant_cause_pct": 76.5,
      "dominant_priority": "Low",
      "dominant_priority_pct": 100.0,
      "associated_police_station": "Wilson Garden",
      "associated_zone": "Central Zone 2",
      "associated_corridor": "Non-corridor",
      "rank": 44
    },
    {
      "cluster_id": 33,
      "center_latitude": 13.002232,
      "center_longitude": 77.680132,
      "event_count": 50,
      "dominant_event_cause": "vehicle_breakdown",
      "dominant_cause_pct": 68.0,
      "dominant_priority": "High",
      "dominant_priority_pct": 64.0,
      "associated_police_station": "K.R. Pura",
      "associated_zone": "East Zone 2",
      "associated_corridor": "ORR East 2",
      "rank": 45
    },
    {
      "cluster_id": 41,
      "center_latitude": 12.975729,
      "center_longitude": 77.547854,
      "event_count": 50,
      "dominant_event_cause": "vehicle_breakdown",
      "dominant_cause_pct": 64.0,
      "dominant_priority": "High",
      "dominant_priority_pct": 100.0,
      "associated_police_station": "Magadi Road",
      "associated_zone": "West Zone 2",
      "associated_corridor": "West of Chord Road",
      "rank": 46
    },
    {
      "cluster_id": 46,
      "center_latitude": 13.041574,
      "center_longitude": 77.614326,
      "event_count": 50,
      "dominant_event_cause": "construction",
      "dominant_cause_pct": 34.0,
      "dominant_priority": "High",
      "dominant_priority_pct": 100.0,
      "associated_police_station": "Hennuru",
      "associated_zone": "North Zone 1",
      "associated_corridor": "ORR North 1",
      "rank": 47
    },
    {
      "cluster_id": 54,
      "center_latitude": 12.96395,
      "center_longitude": 77.595056,
      "event_count": 50,
      "dominant_event_cause": "vehicle_breakdown",
      "dominant_cause_pct": 74.0,
      "dominant_priority": "High",
      "dominant_priority_pct": 66.0,
      "associated_police_station": "Halasuru Gate",
      "associated_zone": "Central Zone 2",
      "associated_corridor": "Mysore Road",
      "rank": 48
    },
    {
      "cluster_id": 48,
      "center_latitude": 13.038181,
      "center_longitude": 77.626045,
      "event_count": 48,
      "dominant_event_cause": "vehicle_breakdown",
      "dominant_cause_pct": 35.4,
      "dominant_priority": "High",
      "dominant_priority_pct": 100.0,
      "associated_police_station": "Hennuru",
      "associated_zone": "North Zone 1",
      "associated_corridor": "Hennur Main Road",
      "rank": 49
    },
    {
      "cluster_id": 4,
      "center_latitude": 12.926511,
      "center_longitude": 77.548844,
      "event_count": 44,
      "dominant_event_cause": "vehicle_breakdown",
      "dominant_cause_pct": 75.0,
      "dominant_priority": "High",
      "dominant_priority_pct": 95.5,
      "associated_police_station": "Banashankari",
      "associated_zone": "West Zone 2",
      "associated_corridor": "ORR West 1",
      "rank": 50
    },
    {
      "cluster_id": 14,
      "center_latitude": 12.954137,
      "center_longitude": 77.70048,
      "event_count": 43,
      "dominant_event_cause": "vehicle_breakdown",
      "dominant_cause_pct": 48.8,
      "dominant_priority": "High",
      "dominant_priority_pct": 100.0,
      "associated_police_station": "HAL Old Airport",
      "associated_zone": "East Zone 1",
      "associated_corridor": "Varthur Road",
      "rank": 51
    },
    {
      "cluster_id": 35,
      "center_latitude": 12.927545,
      "center_longitude": 77.621133,
      "event_count": 43,
      "dominant_event_cause": "pot_holes",
      "dominant_cause_pct": 55.8,
      "dominant_priority": "High",
      "dominant_priority_pct": 100.0,
      "associated_police_station": "Adugodi",
      "associated_zone": "South Zone 2",
      "associated_corridor": "IRR(Thanisandra road)",
      "rank": 52
    },
    {
      "cluster_id": 12,
      "center_latitude": 12.921867,
      "center_longitude": 77.663054,
      "event_count": 42,
      "dominant_event_cause": "vehicle_breakdown",
      "dominant_cause_pct": 69.0,
      "dominant_priority": "High",
      "dominant_priority_pct": 100.0,
      "associated_police_station": "Bellandur",
      "associated_zone": "East Zone 1",
      "associated_corridor": "ORR East 1",
      "rank": 53
    },
    {
      "cluster_id": 60,
      "center_latitude": 13.051266,
      "center_longitude": 77.59329,
      "event_count": 42,
      "dominant_event_cause": "vehicle_breakdown",
      "dominant_cause_pct": 71.4,
      "dominant_priority": "High",
      "dominant_priority_pct": 100.0,
      "associated_police_station": "Kodigehalli",
      "associated_zone": "North Zone 1",
      "associated_corridor": "Bellary Road 1",
      "rank": 54
    },
    {
      "cluster_id": 3,
      "center_latitude": 12.845501,
      "center_longitude": 77.672338,
      "event_count": 40,
      "dominant_event_cause": "vehicle_breakdown",
      "dominant_cause_pct": 80.0,
      "dominant_priority": "Low",
      "dominant_priority_pct": 100.0,
      "associated_police_station": "Electronic City",
      "associated_zone": "South Zone 1",
      "associated_corridor": "Non-corridor",
      "rank": 55
    },
    {
      "cluster_id": 47,
      "center_latitude": 13.041261,
      "center_longitude": 77.622258,
      "event_count": 40,
      "dominant_event_cause": "congestion",
      "dominant_cause_pct": 50.0,
      "dominant_priority": "High",
      "dominant_priority_pct": 100.0,
      "associated_police_station": "Hennuru",
      "associated_zone": "North Zone 1",
      "associated_corridor": "Hennur Main Road",
      "rank": 56
    },
    {
      "cluster_id": 57,
      "center_latitude": 12.964822,
      "center_longitude": 77.568669,
      "event_count": 38,
      "dominant_event_cause": "vehicle_breakdown",
      "dominant_cause_pct": 44.7,
      "dominant_priority": "High",
      "dominant_priority_pct": 81.6,
      "associated_police_station": "Chamarajpet",
      "associated_zone": "Central Zone 2",
      "associated_corridor": "Mysore Road",
      "rank": 57
    },
    {
      "cluster_id": 37,
      "center_latitude": 13.034836,
      "center_longitude": 77.529092,
      "event_count": 37,
      "dominant_event_cause": "vehicle_breakdown",
      "dominant_cause_pct": 73.0,
      "dominant_priority": "High",
      "dominant_priority_pct": 100.0,
      "associated_police_station": "Peenya",
      "associated_zone": "West Zone 1",
      "associated_corridor": "Tumkur Road",
      "rank": 58
    },
    {
      "cluster_id": 66,
      "center_latitude": 13.023778,
      "center_longitude": 77.584969,
      "event_count": 37,
      "dominant_event_cause": "vehicle_breakdown",
      "dominant_cause_pct": 75.7,
      "dominant_priority": "High",
      "dominant_priority_pct": 100.0,
      "associated_police_station": "R.T. Nagar",
      "associated_zone": "North Zone 2",
      "associated_corridor": "Bellary Road 1",
      "rank": 59
    },
    {
      "cluster_id": 67,
      "center_latitude": 13.019424,
      "center_longitude": 77.584056,
      "event_count": 37,
      "dominant_event_cause": "vehicle_breakdown",
      "dominant_cause_pct": 67.6,
      "dominant_priority": "High",
      "dominant_priority_pct": 100.0,
      "associated_police_station": "R.T. Nagar",
      "associated_zone": "North Zone 2",
      "associated_corridor": "Bellary Road 1",
      "rank": 60
    },
    {
      "cluster_id": 26,
      "center_latitude": 12.986335,
      "center_longitude": 77.646818,
      "event_count": 36,
      "dominant_event_cause": "vehicle_breakdown",
      "dominant_cause_pct": 94.4,
      "dominant_priority": "High",
      "dominant_priority_pct": 100.0,
      "associated_police_station": "Banaswadi",
      "associated_zone": "Central Zone 1",
      "associated_corridor": "Old Madras Road",
      "rank": 61
    },
    {
      "cluster_id": 61,
      "center_latitude": 12.98599,
      "center_longitude": 77.588441,
      "event_count": 36,
      "dominant_event_cause": "vehicle_breakdown",
      "dominant_cause_pct": 77.8,
      "dominant_priority": "High",
      "dominant_priority_pct": 100.0,
      "associated_police_station": "High ground",
      "associated_zone": "Central Zone 2",
      "associated_corridor": "Bellary Road 1",
      "rank": 62
    },
    {
      "cluster_id": 5,
      "center_latitude": 12.90647,
      "center_longitude": 77.547377,
      "event_count": 35,
      "dominant_event_cause": "vehicle_breakdown",
      "dominant_cause_pct": 31.4,
      "dominant_priority": "Low",
      "dominant_priority_pct": 100.0,
      "associated_police_station": "K.S. Layout",
      "associated_zone": "South Zone 1",
      "associated_corridor": "Non-corridor",
      "rank": 63
    },
    {
      "cluster_id": 29,
      "center_latitude": 12.997941,
      "center_longitude": 77.551445,
      "event_count": 35,
      "dominant_event_cause": "vehicle_breakdown",
      "dominant_cause_pct": 54.3,
      "dominant_priority": "High",
      "dominant_priority_pct": 97.1,
      "associated_police_station": "Rajajinagar",
      "associated_zone": "West Zone 1",
      "associated_corridor": "West of Chord Road",
      "rank": 64
    },
    {
      "cluster_id": 28,
      "center_latitude": 13.018238,
      "center_longitude": 77.657411,
      "event_count": 33,
      "dominant_event_cause": "vehicle_breakdown",
      "dominant_cause_pct": 51.5,
      "dominant_priority": "High",
      "dominant_priority_pct": 100.0,
      "associated_police_station": "Banaswadi",
      "associated_zone": "East Zone 2",
      "associated_corridor": "ORR North 1",
      "rank": 65
    },
    {
      "cluster_id": 6,
      "center_latitude": 12.96258,
      "center_longitude": 77.504359,
      "event_count": 32,
      "dominant_event_cause": "vehicle_breakdown",
      "dominant_cause_pct": 84.4,
      "dominant_priority": "Low",
      "dominant_priority_pct": 100.0,
      "associated_police_station": "Jnanabharathi",
      "associated_zone": "West Zone 1",
      "associated_corridor": "Non-corridor",
      "rank": 66
    },
    {
      "cluster_id": 25,
      "center_latitude": 12.984071,
      "center_longitude": 77.640982,
      "event_count": 32,
      "dominant_event_cause": "vehicle_breakdown",
      "dominant_cause_pct": 62.5,
      "dominant_priority": "High",
      "dominant_priority_pct": 100.0,
      "associated_police_station": "Jeevanbheemanagar",
      "associated_zone": "Central Zone 1",
      "associated_corridor": "Old Madras Road",
      "rank": 67
    },
    {
      "cluster_id": 10,
      "center_latitude": 12.936184,
      "center_longitude": 77.705466,
      "event_count": 30,
      "dominant_event_cause": "construction",
      "dominant_cause_pct": 53.3,
      "dominant_priority": "Low",
      "dominant_priority_pct": 100.0,
      "associated_police_station": "HAL Old Airport",
      "associated_zone": "East Zone 1",
      "associated_corridor": "Non-corridor",
      "rank": 68
    },
    {
      "cluster_id": 16,
      "center_latitude": 12.854967,
      "center_longitude": 77.588792,
      "event_count": 30,
      "dominant_event_cause": "pot_holes",
      "dominant_cause_pct": 60.0,
      "dominant_priority": "High",
      "dominant_priority_pct": 80.0,
      "associated_police_station": "Hulimavu",
      "associated_zone": "South Zone 1",
      "associated_corridor": "Bannerghata Road",
      "rank": 69
    }
  ]
}